conflow/__init__.py
conflow/froms/__init__.py
conflow/froms/environment.py
conflow/froms/yml.py
conflow/layer.py
conflow/manager.py
conflow/merge.py
conflow/node.py
conflow/policy.py
conflow-0.0.2.dist-info/LICENSE
conflow-0.0.2.dist-info/WHEEL
conflow-0.0.2.dist-info/METADATA
conflow-0.0.2.dist-info/RECORD
