Metadata-Version: 2.1
Name: conflow
Version: 0.0.2
Summary: Python configuration manager.
Home-page: https://github.com/singulared/conflow
License: MIT
Keywords: development,configuration,management
Author: Belousow Makc
Author-email: lib.bmw@gmail.com
Requires-Python: >=3.6,<4.0
Classifier: License :: OSI Approved :: MIT License
Classifier: Programming Language :: Python :: 3
Classifier: Programming Language :: Python :: 3.6
Classifier: Programming Language :: Python :: 3.7
Classifier: Topic :: Software Development :: Libraries
Requires-Dist: PyYAML (>=5.1,<6.0)
Requires-Dist: typing_extensions (>=3.7,<4.0)
Project-URL: Repository, https://github.com/singulared/conflow
